{
  "muke_explosion": {
    "sounds": ["hbmsntm:explosion/muke_explosion"]
  },
  "nuclear_explosion": {
    "sounds": ["hbmsntm:explosion/nuclear_explosion"]
  },
  "weapon.explosion_large_near": {
    "sounds": ["hbmsntm:weapon/explosion_large_near"]
  },
  "weapon.explosion_large_far": {
    "sounds": ["hbmsntm:weapon/explosion_large_far"]
  },
  "weapon.explosion_small_near": {
    "sounds": [
      "hbmsntm:weapon/explosion_small_near1",
      "hbmsntm:weapon/explosion_small_near2",
      "hbmsntm:weapon/explosion_small_near3"
    ]
  },
  "weapon.explosion_small_far": {
    "sounds": [
      "hbmsntm:weapon/explosion_small_far1",
      "hbmsntm:weapon/explosion_small_far2"
    ]
  },
  "grenade_bounce": {
    "sounds": [
      "hbmsntm:weapon/grenade_bounce1",
      "hbmsntm:weapon/grenade_bounce2",
      "hbmsntm:weapon/grenade_bounce3"
    ]
  },
  "duck": {
    "sounds": [
      "hbmsntm:entity/ducc1",
      "hbmsntm:entity/ducc2"
    ]
  },
  "vomit": {
    "sounds": ["hbmsntm:entity/vomit"]
  },
  "tech_boop": {
    "sounds": ["hbmsntm:tech/tech_boop"]
  },
  "tech_bleep": {
    "sounds": ["hbmsntm:tech/tech_bleep"]
  },
  "item.geiger1": {
    "sounds": ["hbmsntm:tool/geiger1"]
  },
  "item.geiger2": {
    "sounds": ["hbmsntm:tool/geiger2"]
  },
  "item.geiger3": {
    "sounds": ["hbmsntm:tool/geiger3"]
  },
  "item.geiger4": {
    "sounds": ["hbmsntm:tool/geiger4"]
  },
  "item.geiger5": {
    "sounds": ["hbmsntm:tool/geiger5"]
  },
  "item.geiger6": {
    "sounds": ["hbmsntm:tool/geiger6"]
  },
  "lock_open": {
    "sounds": ["hbmsntm:block/lock_open"]
  },
  "pin_unlock": {
    "sounds": ["hbmsntm:tool/pin_unlock"]
  },
  "pin_break": {
    "sounds": ["hbmsntm:tool/pin_break"]
  },
  "crate_close": {
    "sounds": ["hbmsntm:block/crate_close"]
  },
  "crate_open": {
    "sounds": ["hbmsntm:block/crate_open"]
  },
  "player.cough": {
    "sounds": [
      "hbmsntm:player/cough1",
      "hbmsntm:player/cough2",
      "hbmsntm:player/cough3",
      "hbmsntm:player/cough4"
    ]
  }
}